{
  "BEL": {
    "BTC": {
      "TYPE": "5",
      "MARKET": "CCCAGG",
      "FROMSYMBOL": "BEL",
      "TOSYMBOL": "BTC",
      "FLAGS": "1",
      "PRICE": 0.00001346828700176515,
      "LASTUPDATE": 1711790014,
      "MEDIAN": 0.00001346828700176515,
      "LASTVOLUME": 17.11,
      "LASTVOLUMETO": 0.0002304423906002017,
      "LASTTRADEID": "14981447",
      "VOLUMEDAY": 754849.350260613,
      "VOLUMEDAYTO": 10.16652769240588,
      "VOLUME24HOUR": 2169742.49620709,
      "VOLUME24HOURTO": 29.22271465884342,
      "OPENDAY": 0.00001365839645383782,
      "HIGHDAY": 0.00001382566323901811,
      "LOWDAY": 0.00001334650410610749,
      "OPEN24HOUR": 0.00001398655399649848,
      "HIGH24HOUR": 0.00001434544495734106,
      "LOW24HOUR": 0.00001327826467029649,
      "LASTMARKET": "CCCAGG",
      "VOLUMEHOUR": 6359.5146094494,
      "VOLUMEHOURTO": 0.08565176795198291,
      "OPENHOUR": 0.00001350763224980068,
      "HIGHHOUR": 0.00001351934523835859,
      "LOWHOUR": 0.00001344333662621531,
      "TOPTIERVOLUME24HOUR": 2169742.49620709,
      "TOPTIERVOLUME24HOURTO": 29.22271465884342,
      "CHANGE24HOUR": -5.182669947333299e-7,
      "CHANGEPCT24HOUR": -3.705465941525536,
      "CHANGEDAY": -1.9010945207267127e-7,
      "CHANGEPCTDAY": -1.391887054349291,
      "CHANGEHOUR": -3.934524803553093e-8,
      "CHANGEPCTHOUR": -0.2912816051540899,
      "CONVERSIONTYPE": "divide",
      "CONVERSIONSYMBOL": "USDT",
      "CONVERSIONLASTUPDATE": 1711790036,
      "SUPPLY": 100000000,
      "MKTCAP": 1346.828700176515,
      "MKTCAPPENALTY": 0,
      "CIRCULATINGSUPPLY": 0,
      "CIRCULATINGSUPPLYMKTCAP": 0,
      "TOTALVOLUME24H": 3983161.72892524,
      "TOTALVOLUME24HTO": 53.64636533961221,
      "TOTALTOPTIERVOLUME24H": 2374831.592,
      "TOTALTOPTIERVOLUME24HTO": 31.984913461914836,
      "IMAGEURL": "/media/37746913/bel.png"
    }
  }
}