{
  "SGB": {
    "BTC": {
      "TYPE": "5",
      "MARKET": "CCCAGG",
      "FROMSYMBOL": "SGB",
      "TOSYMBOL": "BTC",
      "FLAGS": "1",
      "PRICE": 2.669512591469177e-7,
      "LASTUPDATE": 1707464022,
      "MEDIAN": 2.669512591469177e-7,
      "LASTVOLUME": 937.8170136,
      "LASTVOLUMETO": 0.000250351432629922,
      "LASTTRADEID": "2161931",
      "VOLUMEDAY": 3126607.93328259,
      "VOLUMEDAYTO": 0.8346519246485293,
      "VOLUME24HOUR": 12005927.6634983,
      "VOLUME24HOURTO": 3.204997506997682,
      "OPENDAY": 2.776624597460857e-7,
      "HIGHDAY": 2.82600886463309e-7,
      "LOWDAY": 2.662379007565001e-7,
      "OPEN24HOUR": 2.736695543512312e-7,
      "HIGH24HOUR": 2.937702375138119e-7,
      "LOW24HOUR": 2.600753953882809e-7,
      "LASTMARKET": "CCCAGG",
      "VOLUMEHOUR": 273419.10083723,
      "VOLUMEHOURTO": 0.07298957324331659,
      "OPENHOUR": 2.675307429530647e-7,
      "HIGHHOUR": 2.680292585539933e-7,
      "LOWHOUR": 2.662600127718197e-7,
      "TOPTIERVOLUME24HOUR": 12005927.6634983,
      "TOPTIERVOLUME24HOURTO": 3.204997506997682,
      "CHANGE24HOUR": -6.718295204313511e-9,
      "CHANGEPCT24HOUR": -2.454893172256626,
      "CHANGEDAY": -1.0711200599168005e-8,
      "CHANGEPCTDAY": -3.8576336927084376,
      "CHANGEHOUR": -5.794838061469844e-10,
      "CHANGEPCTHOUR": -0.21660456654458154,
      "CONVERSIONTYPE": "divide",
      "CONVERSIONSYMBOL": "USDT",
      "CONVERSIONLASTUPDATE": 1707464044,
      "SUPPLY": 0,
      "MKTCAP": 0,
      "MKTCAPPENALTY": 0,
      "CIRCULATINGSUPPLY": 14625745909.579647,
      "CIRCULATINGSUPPLYMKTCAP": 3904.361286525168,
      "TOTALVOLUME24H": 50003009.6034552,
      "TOTALVOLUME24HTO": 13.348366374777784,
      "TOTALTOPTIERVOLUME24H": 24254485.36011744,
      "TOTALTOPTIERVOLUME24HTO": 6.474765406843831,
      "IMAGEURL": "/media/38554096/sgb.png"
    }
  }
}