{
  "DOT": {
    "BTC": {
      "TYPE": "5",
      "MARKET": "CCCAGG",
      "FROMSYMBOL": "DOT",
      "TOSYMBOL": "BTC",
      "FLAGS": "1",
      "PRICE": 0.0001357654747442706,
      "LASTUPDATE": 1711790042,
      "MEDIAN": 0.0001357654747442706,
      "LASTVOLUME": 10.686,
      "LASTVOLUMETO": 0.001450789863117276,
      "LASTTRADEID": "87159497",
      "VOLUMEDAY": 1971337.85038149,
      "VOLUMEDAYTO": 267.639619138393,
      "VOLUME24HOUR": 8101951.7620832,
      "VOLUME24HOURTO": 1099.965327334406,
      "OPENDAY": 0.0001374407933468609,
      "HIGHDAY": 0.000139099535716589,
      "LOWDAY": 0.0001347066116773957,
      "OPEN24HOUR": 0.0001349602416445043,
      "HIGH24HOUR": 0.0001421006402826701,
      "LOW24HOUR": 0.0001329713610311388,
      "LASTMARKET": "CCCAGG",
      "VOLUMEHOUR": 46530.0831892,
      "VOLUMEHOURTO": 6.317178834072144,
      "OPENHOUR": 0.0001359705943133439,
      "HIGHHOUR": 0.0001362091515271392,
      "LOWHOUR": 0.0001356903391511946,
      "TOPTIERVOLUME24HOUR": 8101951.7620832,
      "TOPTIERVOLUME24HOURTO": 1099.965327334406,
      "CHANGE24HOUR": 8.052330997663126e-7,
      "CHANGEPCT24HOUR": 0.5966446784285989,
      "CHANGEDAY": -0.0000016753186025903009,
      "CHANGEPCTDAY": -1.2189383965226976,
      "CHANGEHOUR": -2.0511956907328624e-7,
      "CHANGEPCTHOUR": -0.15085583034269065,
      "CONVERSIONTYPE": "divide",
      "CONVERSIONSYMBOL": "USDT",
      "CONVERSIONLASTUPDATE": 1711790042,
      "SUPPLY": 1418840903.72617,
      "MKTCAP": 192629.60888097342,
      "MKTCAPPENALTY": 0,
      "CIRCULATINGSUPPLY": 621704316.556166,
      "CIRCULATINGSUPPLYMKTCAP": 84405.98168781017,
      "TOTALVOLUME24H": 20965674.5673934,
      "TOTALVOLUME24HTO": 2846.4147609760457,
      "TOTALTOPTIERVOLUME24H": 10510897.91468738,
      "TOTALTOPTIERVOLUME24HTO": 1427.0170453760968,
      "IMAGEURL": "/media/39334571/dot.png"
    }
  }
}