{
  "GFAL": {
    "BTC": {
      "TYPE": "2",
      "MARKET": "bitget",
      "FROMSYMBOL": "GFAL",
      "TOSYMBOL": "BTC",
      "FLAGS": "2",
      "PRICE": 7.386140571342315e-7,
      "LASTUPDATE": 1707464020,
      "LASTVOLUME": 464,
      "LASTVOLUMETO": 0.0003427169225102834,
      "LASTTRADEID": "1139752200868859905",
      "VOLUMEDAY": 517086,
      "VOLUMEDAYTO": 0.3819269883473113,
      "VOLUME24HOUR": 2078719,
      "VOLUME24HOURTO": 1.535371074232013,
      "OPENDAY": 7.414313850447837e-7,
      "HIGHDAY": 7.582694201504014e-7,
      "LOWDAY": 7.033219498759126e-7,
      "OPEN24HOUR": 7.131271838767764e-7,
      "HIGH24HOUR": 7.707651099150545e-7,
      "LOW24HOUR": 6.825264155307551e-7,
      "VOLUMEHOUR": 41319,
      "VOLUMEHOURTO": 0.03051879422672931,
      "OPENHOUR": 7.319575906449355e-7,
      "HIGHHOUR": 7.427573829359401e-7,
      "LOWHOUR": 7.261751262414135e-7,
      "CHANGE24HOUR": 2.5486873257455066e-8,
      "CHANGEPCT24HOUR": 3.573959012318205,
      "CHANGEDAY": -2.8173279105522256e-9,
      "CHANGEPCTDAY": -0.3799849813994661,
      "CHANGEHOUR": 6.65646648929602e-9,
      "CHANGEPCTHOUR": 0.9094060331324575,
      "CONVERSIONTYPE": "divide",
      "CONVERSIONSYMBOL": "USDT",
      "CONVERSIONLASTUPDATE": 1707464074,
      "SUPPLY": 0,
      "MKTCAP": 0,
      "MKTCAPPENALTY": 0,
      "CIRCULATINGSUPPLY": 0,
      "CIRCULATINGSUPPLYMKTCAP": 0,
      "TOTALVOLUME24H": 9323899.34,
      "TOTALVOLUME24HTO": 6.886763119828584,
      "TOTALTOPTIERVOLUME24H": 0,
      "TOTALTOPTIERVOLUME24HTO": 0,
      "IMAGEURL": "/media/44213562/gfal.png"
    }
  }
}