{
  "SNT": {
    "BTC": {
      "TYPE": "5",
      "MARKET": "CCCAGG",
      "FROMSYMBOL": "SNT",
      "TOSYMBOL": "BTC",
      "FLAGS": "1",
      "PRICE": 7.21287258260094e-7,
      "LASTUPDATE": 1711789964,
      "MEDIAN": 7.21287258260094e-7,
      "LASTVOLUME": 263.9935,
      "LASTVOLUMETO": 0.0001904151478134861,
      "LASTTRADEID": "16109346",
      "VOLUMEDAY": 12116103.9080793,
      "VOLUMEDAYTO": 8.739191368652929,
      "VOLUME24HOUR": 33801688.2833142,
      "VOLUME24HOURTO": 24.38072706643404,
      "OPENDAY": 7.41829195248027e-7,
      "HIGHDAY": 7.435803976933505e-7,
      "LOWDAY": 7.135437666790349e-7,
      "OPEN24HOUR": 7.247867752662293e-7,
      "HIGH24HOUR": 7.594186397844521e-7,
      "LOW24HOUR": 7.1035215201979e-7,
      "LASTMARKET": "CCCAGG",
      "VOLUMEHOUR": 231655.638181178,
      "VOLUMEHOURTO": 0.1670902601241942,
      "OPENHOUR": 7.224482640651506e-7,
      "HIGHHOUR": 7.23052404675166e-7,
      "LOWHOUR": 7.19510604968584e-7,
      "TOPTIERVOLUME24HOUR": 33801688.2833142,
      "TOPTIERVOLUME24HOURTO": 24.38072706643404,
      "CHANGE24HOUR": -3.4995170061352646e-9,
      "CHANGEPCT24HOUR": -0.4828340038144073,
      "CHANGEDAY": -2.0541936987932993e-8,
      "CHANGEPCTDAY": -2.769092551158612,
      "CHANGEHOUR": -1.161005805056626e-9,
      "CHANGEPCTHOUR": -0.1607043525198264,
      "CONVERSIONTYPE": "divide",
      "CONVERSIONSYMBOL": "USDT",
      "CONVERSIONLASTUPDATE": 1711789982,
      "SUPPLY": 6804870174.87817,
      "MKTCAP": 4908.266151253762,
      "MKTCAPPENALTY": 0,
      "CIRCULATINGSUPPLY": 0,
      "CIRCULATINGSUPPLYMKTCAP": 0,
      "TOTALVOLUME24H": 59470310.9947872,
      "TOTALVOLUME24HTO": 42.89517756530518,
      "TOTALTOPTIERVOLUME24H": 26782028.79047,
      "TOTALTOPTIERVOLUME24HTO": 19.31753611692101,
      "IMAGEURL": "/media/37747590/snt.png"
    }
  }
}