{
  "ACM": {
    "BTC": {
      "TYPE": "5",
      "MARKET": "CCCAGG",
      "FROMSYMBOL": "ACM",
      "TOSYMBOL": "BTC",
      "FLAGS": "2",
      "PRICE": 0.00003962083597923292,
      "LASTUPDATE": 1711790046,
      "MEDIAN": 0.00003962083597923292,
      "LASTVOLUME": 3.95066786,
      "LASTVOLUMETO": 0.0001565287632894871,
      "LASTTRADEID": "2649115",
      "VOLUMEDAY": 229707.10980589,
      "VOLUMEDAYTO": 9.101187720882814,
      "VOLUME24HOUR": 528246.12160524,
      "VOLUME24HOURTO": 20.92955294078714,
      "OPENDAY": 0.00004082956411101846,
      "HIGHDAY": 0.00004100991579335531,
      "LOWDAY": 0.00003928507812535478,
      "OPEN24HOUR": 0.00003973322773091336,
      "HIGH24HOUR": 0.00004162146253982766,
      "LOW24HOUR": 0.00003882934825001838,
      "LASTMARKET": "CCCAGG",
      "VOLUMEHOUR": 8056.85061494,
      "VOLUMEHOURTO": 0.3192191567237196,
      "OPENHOUR": 0.00003956914204100859,
      "HIGHHOUR": 0.00003968856205124439,
      "LOWHOUR": 0.00003946707918888089,
      "TOPTIERVOLUME24HOUR": 528246.12160524,
      "TOPTIERVOLUME24HOURTO": 20.92955294078714,
      "CHANGE24HOUR": -1.1239175168044043e-7,
      "CHANGEPCT24HOUR": -0.2828658986417987,
      "CHANGEDAY": -0.000001208728131785544,
      "CHANGEPCTDAY": -2.9604237960976683,
      "CHANGEHOUR": 5.169393822433043e-8,
      "CHANGEPCTHOUR": 0.13064204973349175,
      "CONVERSIONTYPE": "divide",
      "CONVERSIONSYMBOL": "USDT",
      "CONVERSIONLASTUPDATE": 1711790054,
      "SUPPLY": 19920000,
      "MKTCAP": 789.2470527063197,
      "MKTCAPPENALTY": 0,
      "CIRCULATINGSUPPLY": 6038503,
      "CIRCULATINGSUPPLYMKTCAP": 239.2505369231059,
      "TOTALVOLUME24H": 1031334.27351192,
      "TOTALVOLUME24HTO": 40.86232609057712,
      "TOTALTOPTIERVOLUME24H": 512466.27999999997,
      "TOTALTOPTIERVOLUME24HTO": 20.304342424767647,
      "IMAGEURL": "/media/37746336/acm.png"
    }
  }
}