{
  "SOUL": {
    "BTC": {
      "TYPE": "5",
      "MARKET": "CCCAGG",
      "FROMSYMBOL": "SOUL",
      "TOSYMBOL": "BTC",
      "FLAGS": "1",
      "PRICE": 0.000002746436670743988,
      "LASTUPDATE": 1711875820,
      "MEDIAN": 0.000002746436670743988,
      "LASTVOLUME": 84.9378708228,
      "LASTVOLUMETO": 0.0002332764831626537,
      "LASTTRADEID": "3446711",
      "VOLUMEDAY": 372483.419976711,
      "VOLUMEDAYTO": 1.023002123868173,
      "VOLUME24HOUR": 1008039.25294541,
      "VOLUME24HOURTO": 2.768515969838649,
      "OPENDAY": 0.000002657021981840472,
      "HIGHDAY": 0.000002894728752727362,
      "LOWDAY": 0.000002581597726192539,
      "OPEN24HOUR": 0.000002592052660061738,
      "HIGH24HOUR": 0.000002895610265642783,
      "LOW24HOUR": 0.000002515623333473381,
      "LASTMARKET": "CCCAGG",
      "VOLUMEHOUR": 403.0660151,
      "VOLUMEHOURTO": 0.00110699528460129,
      "OPENHOUR": 0.000002744401832930419,
      "HIGHHOUR": 0.000002746905017288697,
      "LOWHOUR": 0.000002743552280821244,
      "TOPTIERVOLUME24HOUR": 1008039.25294541,
      "TOPTIERVOLUME24HOURTO": 2.768515969838649,
      "CHANGE24HOUR": 1.5438401068224986e-7,
      "CHANGEPCT24HOUR": 5.956052246198297,
      "CHANGEDAY": 8.941468890351593e-8,
      "CHANGEPCTDAY": 3.3652220235520955,
      "CHANGEHOUR": 2.0348378135690006e-9,
      "CHANGEPCTHOUR": 0.07414503915398717,
      "CONVERSIONTYPE": "divide",
      "CONVERSIONSYMBOL": "USDT",
      "CONVERSIONLASTUPDATE": 1711875877,
      "SUPPLY": 124129197.66163056,
      "MKTCAP": 340.912980367931,
      "MKTCAPPENALTY": 0,
      "CIRCULATINGSUPPLY": 124129197.66163056,
      "CIRCULATINGSUPPLYMKTCAP": 340.912980367931,
      "TOTALVOLUME24H": 1087820.16267178,
      "TOTALVOLUME24HTO": 2.987629185936467,
      "TOTALTOPTIERVOLUME24H": 0,
      "TOTALTOPTIERVOLUME24HTO": 0,
      "IMAGEURL": "/media/37622143/soul.png"
    }
  }
}