{
  "CORGIAI": {
    "BTC": {
      "TYPE": "5",
      "MARKET": "CCCAGG",
      "FROMSYMBOL": "CORGIAI",
      "TOSYMBOL": "BTC",
      "FLAGS": "2",
      "PRICE": 3.692585218702952e-8,
      "LASTUPDATE": 1711876005,
      "MEDIAN": 3.692585218702952e-8,
      "LASTVOLUME": 4793,
      "LASTVOLUMETO": 0.0001769856095324325,
      "LASTTRADEID": "167727",
      "VOLUMEDAY": 11487138,
      "VOLUMEDAYTO": 0.4241723598400099,
      "VOLUME24HOUR": 27315293,
      "VOLUME24HOURTO": 1.008640471763402,
      "OPENDAY": 3.747598283638527e-8,
      "HIGHDAY": 4.004461873017347e-8,
      "LOWDAY": 3.549787773463106e-8,
      "OPEN24HOUR": 4.063098883329385e-8,
      "HIGH24HOUR": 4.090782230596472e-8,
      "LOW24HOUR": 3.549787773463106e-8,
      "LASTMARKET": "CCCAGG",
      "VOLUMEHOUR": 110163,
      "VOLUMEHOURTO": 0.004067862654479734,
      "OPENHOUR": 3.701873953572806e-8,
      "HIGHHOUR": 3.731891044738008e-8,
      "LOWHOUR": 3.684734311576182e-8,
      "TOPTIERVOLUME24HOUR": 27315293,
      "TOPTIERVOLUME24HOURTO": 1.008640471763402,
      "CHANGE24HOUR": -3.7051366462643304e-9,
      "CHANGEPCT24HOUR": -9.118992061616444,
      "CHANGEDAY": -5.501306493557498e-10,
      "CHANGEPCTDAY": -1.4679552281725092,
      "CHANGEHOUR": -9.288734869853642e-11,
      "CHANGEPCTHOUR": -0.2509198040330024,
      "CONVERSIONTYPE": "divide",
      "CONVERSIONSYMBOL": "USDT",
      "CONVERSIONLASTUPDATE": 1711876020,
      "SUPPLY": 372459723998.826,
      "MKTCAP": 13753.39271400246,
      "MKTCAPPENALTY": 0,
      "CIRCULATINGSUPPLY": 0,
      "CIRCULATINGSUPPLYMKTCAP": 0,
      "TOTALVOLUME24H": 174054615.397077,
      "TOTALVOLUME24HTO": 6.427115000622738,
      "TOTALTOPTIERVOLUME24H": 134910100,
      "TOTALTOPTIERVOLUME24HTO": 4.9816704111373715,
      "IMAGEURL": "/media/44154246/corgiai.png"
    }
  }
}