{
  "CPOOL": {
    "BTC": {
      "TYPE": "5",
      "MARKET": "CCCAGG",
      "FROMSYMBOL": "CPOOL",
      "TOSYMBOL": "BTC",
      "FLAGS": "1",
      "PRICE": 0.000004225385568370227,
      "LASTUPDATE": 1711875979,
      "MEDIAN": 0.000004225385568370227,
      "LASTVOLUME": 43.94,
      "LASTVOLUMETO": 0.0001856634418741878,
      "LASTTRADEID": "15009506",
      "VOLUMEDAY": 2590993.33246247,
      "VOLUMEDAYTO": 10.9479458347304,
      "VOLUME24HOUR": 8359545.81928542,
      "VOLUME24HOURTO": 35.32230426293828,
      "OPENDAY": 0.000004368073266223333,
      "HIGHDAY": 0.000004385173597844786,
      "LOWDAY": 0.000004123438936320636,
      "OPEN24HOUR": 0.000004699549126739062,
      "HIGH24HOUR": 0.000004828371167805902,
      "LOW24HOUR": 0.000004123438936320636,
      "LASTMARKET": "CCCAGG",
      "VOLUMEHOUR": 72055.45559363,
      "VOLUMEHOURTO": 0.304462082187666,
      "OPENHOUR": 0.000004220210094566879,
      "HIGHHOUR": 0.000004230901180877044,
      "LOWHOUR": 0.000004211964444655226,
      "TOPTIERVOLUME24HOUR": 8359545.81928542,
      "TOPTIERVOLUME24HOURTO": 35.32230426293828,
      "CHANGE24HOUR": -4.741635583688352e-7,
      "CHANGEPCT24HOUR": -10.089554244065308,
      "CHANGEDAY": -1.4268769785310625e-7,
      "CHANGEPCTDAY": -3.2666049573036364,
      "CHANGEHOUR": 5.175473803347898e-9,
      "CHANGEPCTHOUR": 0.1226354538607173,
      "CONVERSIONTYPE": "divide",
      "CONVERSIONSYMBOL": "USDT",
      "CONVERSIONLASTUPDATE": 1711875983,
      "SUPPLY": 1000000000,
      "MKTCAP": 4225.385568370227,
      "MKTCAPPENALTY": 0,
      "CIRCULATINGSUPPLY": 0,
      "CIRCULATINGSUPPLYMKTCAP": 0,
      "TOTALVOLUME24H": 13413136.9599775,
      "TOTALVOLUME24HTO": 56.675675337262234,
      "TOTALTOPTIERVOLUME24H": 3508516.4,
      "TOTALTOPTIERVOLUME24HTO": 14.824834562950265,
      "IMAGEURL": "/media/39501020/cpool.png"
    }
  }
}