{
  "STETH": {
    "BTC": {
      "TYPE": "5",
      "MARKET": "CCCAGG",
      "FROMSYMBOL": "STETH",
      "TOSYMBOL": "BTC",
      "FLAGS": "1",
      "PRICE": 0.0512949794221551,
      "LASTUPDATE": 1711875929,
      "MEDIAN": 0.0512949794221551,
      "LASTVOLUME": 0.02043,
      "LASTVOLUMETO": 0.001047956429594629,
      "LASTTRADEID": "2985206",
      "VOLUMEDAY": 2087.32318899,
      "VOLUMEDAYTO": 107.0692000266292,
      "VOLUME24HOUR": 5145.76289779,
      "VOLUME24HOURTO": 263.9518019534273,
      "OPENDAY": 0.05022499559105428,
      "HIGHDAY": 0.05203618151626908,
      "LOWDAY": 0.0495915855865636,
      "OPEN24HOUR": 0.05002105498307279,
      "HIGH24HOUR": 0.05205202775610505,
      "LOW24HOUR": 0.04928858289211673,
      "LASTMARKET": "CCCAGG",
      "VOLUMEHOUR": 19.959026,
      "VOLUMEHOURTO": 1.023797827956259,
      "OPENHOUR": 0.05131466769092365,
      "HIGHHOUR": 0.0513603561638549,
      "LOWHOUR": 0.05124608564069472,
      "TOPTIERVOLUME24HOUR": 5145.76289779,
      "TOPTIERVOLUME24HOURTO": 263.9518019534273,
      "CHANGE24HOUR": 0.001273924439082308,
      "CHANGEPCT24HOUR": 2.5467764314715193,
      "CHANGEDAY": 0.0010699838311008167,
      "CHANGEPCTDAY": 2.130381134949058,
      "CHANGEHOUR": -0.000019688268768552897,
      "CHANGEPCTHOUR": -0.0383677214615097,
      "CONVERSIONTYPE": "divide",
      "CONVERSIONSYMBOL": "USDT",
      "CONVERSIONLASTUPDATE": 1711875935,
      "SUPPLY": 9693039.32030524,
      "MKTCAP": 497204.2524731975,
      "MKTCAPPENALTY": 0,
      "CIRCULATINGSUPPLY": 9693039.32030524,
      "CIRCULATINGSUPPLYMKTCAP": 497204.2524731975,
      "TOTALVOLUME24H": 11173.4654994174,
      "TOTALVOLUME24HTO": 573.1426828667755,
      "TOTALTOPTIERVOLUME24H": 5489.846173,
      "TOTALTOPTIERVOLUME24HTO": 281.601546474832,
      "IMAGEURL": "/media/37621928/steth.png"
    }
  }
}