{
  "IQT": {
    "BTC": {
      "TYPE": "5",
      "MARKET": "CCCAGG",
      "FROMSYMBOL": "IQT",
      "TOSYMBOL": "BTC",
      "FLAGS": "2",
      "PRICE": 0.000003849802327455386,
      "LASTUPDATE": 1711875980,
      "MEDIAN": 0.000003849802327455386,
      "LASTVOLUME": 36.99,
      "LASTVOLUMETO": 0.0001424041880925747,
      "LASTTRADEID": "104475",
      "VOLUMEDAY": 481097.78312259,
      "VOLUMEDAYTO": 1.852131365198973,
      "VOLUME24HOUR": 1191295.8087078,
      "VOLUME24HOURTO": 4.586253377051134,
      "OPENDAY": 0.000003769444245638269,
      "HIGHDAY": 0.000003901524653490111,
      "LOWDAY": 0.00000369699126279967,
      "OPEN24HOUR": 0.000003763770746996103,
      "HIGH24HOUR": 0.000003966236674445779,
      "LOW24HOUR": 0.000003694148853788287,
      "LASTMARKET": "CCCAGG",
      "VOLUMEHOUR": 3514.92442535,
      "VOLUMEHOURTO": 0.01353176423354222,
      "OPENHOUR": 0.000003844713827300709,
      "HIGHHOUR": 0.000003865085318480999,
      "LOWHOUR": 0.000003844019911670326,
      "TOPTIERVOLUME24HOUR": 1191295.8087078,
      "TOPTIERVOLUME24HOURTO": 4.586253377051134,
      "CHANGE24HOUR": 8.603158045928275e-8,
      "CHANGEPCT24HOUR": 2.2857816334309224,
      "CHANGEDAY": 8.035808181711658e-8,
      "CHANGEPCTDAY": 2.1318283699275082,
      "CHANGEHOUR": 5.08850015467707e-9,
      "CHANGEPCTHOUR": 0.1323505567187974,
      "CONVERSIONTYPE": "divide",
      "CONVERSIONSYMBOL": "USDT",
      "CONVERSIONLASTUPDATE": 1711876000,
      "SUPPLY": 1000000000,
      "MKTCAP": 3849.8023274553857,
      "MKTCAPPENALTY": 0,
      "CIRCULATINGSUPPLY": 0,
      "CIRCULATINGSUPPLYMKTCAP": 0,
      "TOTALVOLUME24H": 1399316.77798653,
      "TOTALVOLUME24HTO": 5.387092988739914,
      "TOTALTOPTIERVOLUME24H": 0,
      "TOTALTOPTIERVOLUME24HTO": 0,
      "IMAGEURL": "/media/44154328/iqt.png"
    }
  }
}