{
  "RDNT": {
    "EUR": {
      "TYPE": "5",
      "MARKET": "CCCAGG",
      "FROMSYMBOL": "RDNT",
      "TOSYMBOL": "EUR",
      "FLAGS": "2",
      "PRICE": 0.3176094304147823,
      "LASTUPDATE": 1711873926,
      "MEDIAN": 0.3176094304147823,
      "LASTVOLUME": 444,
      "LASTVOLUMETO": 141.0185871041634,
      "LASTTRADEID": "17928374",
      "VOLUMEDAY": 13431163.1774483,
      "VOLUMEDAYTO": 4265864.086597353,
      "VOLUME24HOUR": 30016023.8144033,
      "VOLUME24HOURTO": 9533372.227009175,
      "OPENDAY": 0.3076381819680898,
      "HIGHDAY": 0.3194489809351538,
      "LOWDAY": 0.3062942976421254,
      "OPEN24HOUR": 0.3094251422081912,
      "HIGH24HOUR": 0.3194489809351538,
      "LOW24HOUR": 0.3046986399594246,
      "LASTMARKET": "CCCAGG",
      "VOLUMEHOUR": 507688.75946439,
      "VOLUMEHOURTO": 161246.7377214723,
      "OPENHOUR": 0.3174491715707487,
      "HIGHHOUR": 0.3179944594911258,
      "LOWHOUR": 0.3165622404742647,
      "TOPTIERVOLUME24HOUR": 30016023.8144033,
      "TOPTIERVOLUME24HOURTO": 9533372.227009175,
      "CHANGE24HOUR": 0.008184288206591117,
      "CHANGEPCT24HOUR": 2.6449978008200983,
      "CHANGEDAY": 0.009971248446692504,
      "CHANGEPCTDAY": 3.2412259046982625,
      "CHANGEHOUR": 0.00016025884403358948,
      "CHANGEPCTHOUR": 0.050483308316926316,
      "CONVERSIONTYPE": "multiply",
      "CONVERSIONSYMBOL": "USDT",
      "CONVERSIONLASTUPDATE": 1711873924,
      "SUPPLY": 830681994.559542,
      "MKTCAP": 263832435.1478714,
      "MKTCAPPENALTY": 0,
      "CIRCULATINGSUPPLY": 477395727.284,
      "CIRCULATINGSUPPLYMKTCAP": 151625385.025122,
      "TOTALVOLUME24H": 42743750.6775408,
      "TOTALVOLUME24HTO": 13575818.306485202,
      "TOTALTOPTIERVOLUME24H": 30582001.932,
      "TOTALTOPTIERVOLUME24HTO": 9713132.214566294,
      "IMAGEURL": "/media/43881334/rdnt.png"
    }
  }
}