{
  "ALPH": {
    "EUR": {
      "TYPE": "5",
      "MARKET": "CCCAGG",
      "FROMSYMBOL": "ALPH",
      "TOSYMBOL": "EUR",
      "FLAGS": "1",
      "PRICE": 2.327819790786028,
      "LASTUPDATE": 1711873904,
      "MEDIAN": 2.327819790786028,
      "LASTVOLUME": 0.51277164,
      "LASTVOLUMETO": 1.193639971745808,
      "LASTTRADEID": "482522",
      "VOLUMEDAY": 76150.4085965,
      "VOLUMEDAYTO": 177264.4282073752,
      "VOLUME24HOUR": 331070.92346034,
      "VOLUME24HOURTO": 770673.4477847858,
      "OPENDAY": 2.359821165753499,
      "HIGHDAY": 2.380839976663035,
      "LOWDAY": 2.3081835332836,
      "OPEN24HOUR": 2.521619493934077,
      "HIGH24HOUR": 2.539740605977747,
      "LOW24HOUR": 2.307831142574311,
      "LASTMARKET": "CCCAGG",
      "VOLUMEHOUR": 5510.8051284,
      "VOLUMEHOURTO": 12828.16124105466,
      "OPENHOUR": 2.342912062883617,
      "HIGHHOUR": 2.349998460783859,
      "LOWHOUR": 2.322737823395193,
      "TOPTIERVOLUME24HOUR": 331070.92346034,
      "TOPTIERVOLUME24HOURTO": 770673.4477847858,
      "CHANGE24HOUR": -0.19379970314804895,
      "CHANGEPCT24HOUR": -7.685525259233083,
      "CHANGEDAY": -0.03200137496747102,
      "CHANGEPCTDAY": -1.356093225702248,
      "CHANGEHOUR": -0.01509227209758901,
      "CHANGEPCTHOUR": -0.6441672453986043,
      "CONVERSIONTYPE": "multiply",
      "CONVERSIONSYMBOL": "USDT",
      "CONVERSIONLASTUPDATE": 1711873903,
      "SUPPLY": 194573477.82011804,
      "MKTCAP": 452931992.43173707,
      "MKTCAPPENALTY": 0,
      "CIRCULATINGSUPPLY": 74383564.4763733,
      "CIRCULATINGSUPPLYMKTCAP": 173151533.4973103,
      "TOTALVOLUME24H": 367012.95176248,
      "TOTALVOLUME24HTO": 854340.0125874989,
      "TOTALTOPTIERVOLUME24H": 0,
      "TOTALTOPTIERVOLUME24HTO": 0,
      "IMAGEURL": "/media/40219233/alph.png"
    }
  }
}