{
  "HBAR": {
    "EUR": {
      "TYPE": "5",
      "MARKET": "CCCAGG",
      "FROMSYMBOL": "HBAR",
      "TOSYMBOL": "EUR",
      "FLAGS": "2",
      "PRICE": 0.1093668777555733,
      "LASTUPDATE": 1711873755,
      "MEDIAN": 0.1093668777555733,
      "LASTVOLUME": 520,
      "LASTVOLUMETO": 56.87077643289812,
      "LASTTRADEID": "31218414",
      "VOLUMEDAY": 70186333.68235,
      "VOLUMEDAYTO": 7676060.175949449,
      "VOLUME24HOUR": 160496318.443994,
      "VOLUME24HOURTO": 17552981.23948386,
      "OPENDAY": 0.1053709256119799,
      "HIGHDAY": 0.1097133809818197,
      "LOWDAY": 0.1047839150177326,
      "OPEN24HOUR": 0.1065485822354637,
      "HIGH24HOUR": 0.1097133809818197,
      "LOW24HOUR": 0.1045869434944286,
      "LASTMARKET": "CCCAGG",
      "VOLUMEHOUR": 8099467.577464,
      "VOLUMEHOURTO": 885813.4804297347,
      "OPENHOUR": 0.1084666700895599,
      "HIGHHOUR": 0.1096320244107517,
      "LOWHOUR": 0.1081984477287567,
      "TOPTIERVOLUME24HOUR": 160496318.443994,
      "TOPTIERVOLUME24HOURTO": 17552981.23948386,
      "CHANGE24HOUR": 0.0028182955201095927,
      "CHANGEPCT24HOUR": 2.6450802638381323,
      "CHANGEDAY": 0.003995952143593398,
      "CHANGEPCTDAY": 3.7922720336615203,
      "CHANGEHOUR": 0.0009002076660133973,
      "CHANGEPCTHOUR": 0.8299394323344713,
      "CONVERSIONTYPE": "multiply",
      "CONVERSIONSYMBOL": "USDT",
      "CONVERSIONLASTUPDATE": 1711873750,
      "SUPPLY": 50000000000,
      "MKTCAP": 5468343887.778665,
      "MKTCAPPENALTY": 0,
      "CIRCULATINGSUPPLY": 33716486738.3452,
      "CIRCULATINGSUPPLYMKTCAP": 3687466883.4600077,
      "TOTALVOLUME24H": 291105989.518801,
      "TOTALVOLUME24HTO": 31837353.169617914,
      "TOTALTOPTIERVOLUME24H": 195975207.89429003,
      "TOTALTOPTIERVOLUME24HTO": 21433196.604897887,
      "IMAGEURL": "/media/38553139/hbar.png"
    }
  }
}