{
  "GNS": {
    "EUR": {
      "TYPE": "5",
      "MARKET": "CCCAGG",
      "FROMSYMBOL": "GNS",
      "TOSYMBOL": "EUR",
      "FLAGS": "2",
      "PRICE": 4.684322440453887,
      "LASTUPDATE": 1711873854,
      "MEDIAN": 4.684322440453887,
      "LASTVOLUME": 1.44,
      "LASTVOLUMETO": 6.745424314253598,
      "LASTTRADEID": "4622301",
      "VOLUMEDAY": 112950.08,
      "VOLUMEDAYTO": 529094.5943950618,
      "VOLUME24HOUR": 286033.72952649,
      "VOLUME24HOURTO": 1339874.217947655,
      "OPENDAY": 4.558492424928026,
      "HIGHDAY": 4.700989818351694,
      "LOWDAY": 4.549187983464045,
      "OPEN24HOUR": 4.637667506100778,
      "HIGH24HOUR": 4.702154572059936,
      "LOW24HOUR": 4.548493458285667,
      "LASTMARKET": "CCCAGG",
      "VOLUMEHOUR": 23153.26,
      "VOLUMEHOURTO": 108457.3353876634,
      "OPENHOUR": 4.639983048754298,
      "HIGHHOUR": 4.697511089460706,
      "LOWHOUR": 4.6292901857423,
      "TOPTIERVOLUME24HOUR": 286033.72952649,
      "TOPTIERVOLUME24HOURTO": 1339874.217947655,
      "CHANGE24HOUR": 0.04665493435310886,
      "CHANGEPCT24HOUR": 1.0059999836498634,
      "CHANGEDAY": 0.12583001552586026,
      "CHANGEPCTDAY": 2.7603427580083557,
      "CHANGEHOUR": 0.044339391699588226,
      "CHANGEPCTHOUR": 0.9555938294104775,
      "CONVERSIONTYPE": "multiply",
      "CONVERSIONSYMBOL": "USDT",
      "CONVERSIONLASTUPDATE": 1711873895,
      "SUPPLY": 34084856,
      "MKTCAP": 159664455.8404393,
      "MKTCAPPENALTY": 0,
      "CIRCULATINGSUPPLY": 0,
      "CIRCULATINGSUPPLYMKTCAP": 0,
      "TOTALVOLUME24H": 458075.95666529,
      "TOTALVOLUME24HTO": 2145775.4832396004,
      "TOTALTOPTIERVOLUME24H": 275235.82,
      "TOTALTOPTIERVOLUME24HTO": 1289293.3280427272,
      "IMAGEURL": "/media/40219374/gns.png"
    }
  }
}