{
  "PSP": {
    "EUR": {
      "TYPE": "5",
      "MARKET": "CCCAGG",
      "FROMSYMBOL": "PSP",
      "TOSYMBOL": "EUR",
      "FLAGS": "2",
      "PRICE": 0.03520376877654268,
      "LASTUPDATE": 1707463087,
      "MEDIAN": 0.03520376877654268,
      "LASTVOLUME": 234.87,
      "LASTVOLUMETO": 8.26830917254658,
      "LASTTRADEID": "1090213",
      "VOLUMEDAY": 510498.38052016,
      "VOLUMEDAYTO": 17971.46694863121,
      "VOLUME24HOUR": 1664432.67457947,
      "VOLUME24HOURTO": 58594.30302001817,
      "OPENDAY": 0.03397540005150873,
      "HIGHDAY": 0.03545542285623746,
      "LOWDAY": 0.03372406164744068,
      "OPEN24HOUR": 0.03421807560175515,
      "HIGH24HOUR": 0.03553560360703299,
      "LOW24HOUR": 0.03341740928787225,
      "LASTMARKET": "CCCAGG",
      "VOLUMEHOUR": 4452.39804452,
      "VOLUMEHOURTO": 156.7411912604129,
      "OPENHOUR": 0.03518958411342035,
      "HIGHHOUR": 0.03526972533781057,
      "LOWHOUR": 0.03513313382542435,
      "TOPTIERVOLUME24HOUR": 1664432.67457947,
      "TOPTIERVOLUME24HOURTO": 58594.30302001817,
      "CHANGE24HOUR": 0.0009856931747875275,
      "CHANGEPCT24HOUR": 2.8806213016168805,
      "CHANGEDAY": 0.00122836872503395,
      "CHANGEPCTDAY": 3.615465081122429,
      "CHANGEHOUR": 0.0000141846631223283,
      "CHANGEPCTHOUR": 0.040309266164127965,
      "CONVERSIONTYPE": "multiply",
      "CONVERSIONSYMBOL": "USDT",
      "CONVERSIONLASTUPDATE": 1707463171,
      "SUPPLY": 0,
      "MKTCAP": 0,
      "MKTCAPPENALTY": 0,
      "CIRCULATINGSUPPLY": 0,
      "CIRCULATINGSUPPLYMKTCAP": 0,
      "TOTALVOLUME24H": 5582908.01163661,
      "TOTALVOLUME24HTO": 196539.40274236287,
      "TOTALTOPTIERVOLUME24H": 300975.62,
      "TOTALTOPTIERVOLUME24HTO": 10595.47613385658,
      "IMAGEURL": "/media/39109097/psp.png"
    }
  }
}