{
  "YCC": {
    "EUR": {
      "TYPE": "5",
      "MARKET": "CCCAGG",
      "FROMSYMBOL": "YCC",
      "TOSYMBOL": "EUR",
      "FLAGS": "4",
      "PRICE": 0.0007623449262333013,
      "LASTUPDATE": 1708646401,
      "MEDIAN": 0.0007623449262333013,
      "LASTVOLUME": 0,
      "LASTVOLUMETO": 0,
      "LASTTRADEID": "1937",
      "VOLUMEDAY": 0,
      "VOLUMEDAYTO": 0,
      "VOLUME24HOUR": 1160960,
      "VOLUME24HOURTO": 885.0519655598134,
      "OPENDAY": 0.0007627046360218705,
      "HIGHDAY": 0.0007661428883649193,
      "LOWDAY": 0.000758437893060971,
      "OPEN24HOUR": 0.001624201705276137,
      "HIGH24HOUR": 0.001635077819142086,
      "LOW24HOUR": 0.0004751492901104431,
      "LASTMARKET": "CCCAGG",
      "VOLUMEHOUR": 0,
      "VOLUMEHOURTO": 0,
      "OPENHOUR": 0.0007626674718189521,
      "HIGHHOUR": 0.0007626704801272907,
      "LOWHOUR": 0.0007620770996912948,
      "TOPTIERVOLUME24HOUR": 1160960,
      "TOPTIERVOLUME24HOURTO": 885.0519655598134,
      "CHANGE24HOUR": -0.0008618567790428357,
      "CHANGEPCT24HOUR": -53.06340808799409,
      "CHANGEDAY": -3.5970978856918884e-7,
      "CHANGEPCTDAY": -0.04716239702506203,
      "CHANGEHOUR": -3.2254558565085033e-7,
      "CHANGEPCTHOUR": -0.04229177165266839,
      "CONVERSIONTYPE": "multiply",
      "CONVERSIONSYMBOL": "BTC",
      "CONVERSIONLASTUPDATE": 1708671998,
      "SUPPLY": 10000000000,
      "MKTCAP": 7623449.262333013,
      "MKTCAPPENALTY": 0,
      "CIRCULATINGSUPPLY": 0,
      "CIRCULATINGSUPPLYMKTCAP": 0,
      "TOTALVOLUME24H": 1149880,
      "TOTALVOLUME24HTO": 876.6051837771485,
      "TOTALTOPTIERVOLUME24H": 0,
      "TOTALTOPTIERVOLUME24HTO": 0,
      "IMAGEURL": "/media/35650742/ycc.png"
    }
  }
}