{
  "MCB": {
    "EUR": {
      "TYPE": "5",
      "MARKET": "CCCAGG",
      "FROMSYMBOL": "MCB",
      "TOSYMBOL": "EUR",
      "FLAGS": "2",
      "PRICE": 11.87790027103095,
      "LASTUPDATE": 1711873782,
      "MEDIAN": 11.87790027103095,
      "LASTVOLUME": 0.11224078,
      "LASTVOLUMETO": 1.333184791182725,
      "LASTTRADEID": "240489",
      "VOLUMEDAY": 68.20446417,
      "VOLUMEDAYTO": 810.1258234503636,
      "VOLUME24HOUR": 200.76706916,
      "VOLUME24HOURTO": 2384.691225189653,
      "OPENDAY": 11.8575193341222,
      "HIGHDAY": 12.04156210610958,
      "LOWDAY": 11.8119144449435,
      "OPEN24HOUR": 12.08715431360469,
      "HIGH24HOUR": 12.20754122253783,
      "LOW24HOUR": 11.55398018508654,
      "LASTMARKET": "CCCAGG",
      "VOLUMEHOUR": 3.83310426,
      "VOLUMEHOURTO": 45.52923012874388,
      "OPENHOUR": 11.89590057830611,
      "HIGHHOUR": 11.90128376186166,
      "LOWHOUR": 11.87217884152762,
      "TOPTIERVOLUME24HOUR": 200.76706916,
      "TOPTIERVOLUME24HOURTO": 2384.691225189653,
      "CHANGE24HOUR": -0.20925404257374147,
      "CHANGEPCT24HOUR": -1.7312101520720695,
      "CHANGEDAY": 0.020380936908749092,
      "CHANGEPCTDAY": 0.17188196227603175,
      "CHANGEHOUR": -0.018000307275160665,
      "CHANGEPCTHOUR": -0.15131521280521476,
      "CONVERSIONTYPE": "multiply",
      "CONVERSIONSYMBOL": "USDT",
      "CONVERSIONLASTUPDATE": 1711873782,
      "SUPPLY": 4803143.54867189,
      "MKTCAP": 57051260.05857041,
      "MKTCAPPENALTY": 0,
      "CIRCULATINGSUPPLY": 0,
      "CIRCULATINGSUPPLYMKTCAP": 0,
      "TOTALVOLUME24H": 2761.0862205,
      "TOTALVOLUME24HTO": 32795.90676681676,
      "TOTALTOPTIERVOLUME24H": 0,
      "TOTALTOPTIERVOLUME24HTO": 0,
      "IMAGEURL": "/media/37072273/mcb.png"
    }
  }
}