{
  "PCX": {
    "EUR": {
      "TYPE": "5",
      "MARKET": "CCCAGG",
      "FROMSYMBOL": "PCX",
      "TOSYMBOL": "EUR",
      "FLAGS": "1",
      "PRICE": 0.383467894483759,
      "LASTUPDATE": 1707463072,
      "MEDIAN": 0.383467894483759,
      "LASTVOLUME": 21.013,
      "LASTVOLUMETO": 8.057810866787227,
      "LASTTRADEID": "1336566",
      "VOLUMEDAY": 36696.9796755849,
      "VOLUMEDAYTO": 14072.11353010984,
      "VOLUME24HOUR": 122295.251706125,
      "VOLUME24HOURTO": 46896.30267710908,
      "OPENDAY": 0.3842629560307161,
      "HIGHDAY": 0.3872588591489099,
      "LOWDAY": 0.3789152508796299,
      "OPEN24HOUR": 0.3854570939198007,
      "HIGH24HOUR": 0.3913912163320193,
      "LOW24HOUR": 0.3748461720592716,
      "LASTMARKET": "CCCAGG",
      "VOLUMEHOUR": 1891.2523797328,
      "VOLUMEHOURTO": 725.2345679935353,
      "OPENHOUR": 0.3824049769903917,
      "HIGHHOUR": 0.3835488643111346,
      "LOWHOUR": 0.3806602184522987,
      "TOPTIERVOLUME24HOUR": 122295.251706125,
      "TOPTIERVOLUME24HOURTO": 46896.30267710908,
      "CHANGE24HOUR": -0.0019891994360417,
      "CHANGEPCT24HOUR": -0.51606247943528,
      "CHANGEDAY": -0.0007950615469570765,
      "CHANGEPCTDAY": -0.2069055927664084,
      "CHANGEHOUR": 0.001062917493367288,
      "CHANGEPCTHOUR": 0.2779559779092506,
      "CONVERSIONTYPE": "multiply",
      "CONVERSIONSYMBOL": "USDT",
      "CONVERSIONLASTUPDATE": 1707463104,
      "SUPPLY": 0,
      "MKTCAP": 0,
      "MKTCAPPENALTY": 0,
      "CIRCULATINGSUPPLY": 0,
      "CIRCULATINGSUPPLYMKTCAP": 0,
      "TOTALVOLUME24H": 188066.369044581,
      "TOTALVOLUME24HTO": 72117.41456073106,
      "TOTALTOPTIERVOLUME24H": 0,
      "TOTALTOPTIERVOLUME24HTO": 0,
      "IMAGEURL": "/media/36935007/pcx.png"
    }
  }
}