{
  "BNT": {
    "EUR": {
      "TYPE": "5",
      "MARKET": "CCCAGG",
      "FROMSYMBOL": "BNT",
      "TOSYMBOL": "EUR",
      "FLAGS": "2",
      "PRICE": 0.8391846485996117,
      "LASTUPDATE": 1711873722,
      "MEDIAN": 0.8391846485996117,
      "LASTVOLUME": 1,
      "LASTVOLUMETO": 0.8391846485996117,
      "LASTTRADEID": "30490306",
      "VOLUMEDAY": 1632815.44387746,
      "VOLUMEDAYTO": 1370233.654498325,
      "VOLUME24HOUR": 3494008.57139417,
      "VOLUME24HOURTO": 2932118.355189448,
      "OPENDAY": 0.8159563633251692,
      "HIGHDAY": 0.8492152215548976,
      "LOWDAY": 0.8115771994039624,
      "OPEN24HOUR": 0.8186622382504455,
      "HIGH24HOUR": 0.8492152215548976,
      "LOW24HOUR": 0.8074812265566896,
      "LASTMARKET": "CCCAGG",
      "VOLUMEHOUR": 84649.7345592003,
      "VOLUMEHOURTO": 71036.75775011291,
      "OPENHOUR": 0.8394005231083205,
      "HIGHHOUR": 0.842151663699285,
      "LOWHOUR": 0.8370938621620514,
      "TOPTIERVOLUME24HOUR": 3494008.57139417,
      "TOPTIERVOLUME24HOURTO": 2932118.355189448,
      "CHANGE24HOUR": 0.020522410349166242,
      "CHANGEPCT24HOUR": 2.5068226419022905,
      "CHANGEDAY": 0.02322828527444254,
      "CHANGEPCTDAY": 2.8467558215715227,
      "CHANGEHOUR": -0.00021587450870874658,
      "CHANGEPCTHOUR": -0.025717700044950897,
      "CONVERSIONTYPE": "multiply",
      "CONVERSIONSYMBOL": "USDT",
      "CONVERSIONLASTUPDATE": 1711873739,
      "SUPPLY": 131181056.346255,
      "MKTCAP": 110085128.67285785,
      "MKTCAPPENALTY": 0,
      "CIRCULATINGSUPPLY": 0,
      "CIRCULATINGSUPPLYMKTCAP": 0,
      "TOTALVOLUME24H": 6635222.00479233,
      "TOTALVOLUME24HTO": 5568176.446472063,
      "TOTALTOPTIERVOLUME24H": 3870288.6641616398,
      "TOTALTOPTIERVOLUME24HTO": 3247886.8326135464,
      "IMAGEURL": "/media/37747631/bnt.png"
    }
  }
}